{
  "name": "Pset_DistributionPortPHistoryAirConditioning",
  "ifcVersion": {
    "version": "4.0.0.0",
    "schema": "IfcSharedBldgServiceElements"
  },
  "definition": "Fluid flow performance history attached to an instance of IfcPerformanceHistory assigned to IfcDistributionPort.  This replaces the deprecated IfcFluidFlowProperties for performance values.",
  "dictionaryReference": {
    "dictionaryWebUri": "http://bsdd.buildingsmart.org/#concept/browse/",
    "dictionaryApiUri": "http://bsdd.buildingsmart.org/api/4.0/IfdConcept/",
    "ifdGuid": "",
    "legacyGuid": ""
  },
  "localizations": [
    {
      "language": "de-DE",
      "name": "",
      "definition": ""
    },
    {
      "language": "en-GB",
      "name": "",
      "definition": ""
    },
    {
      "language": "es-ES",
      "name": "",
      "definition": ""
    },
    {
      "language": "fr-FR",
      "name": "",
      "definition": ""
    },
    {
      "language": "ja-JP",
      "name": "",
      "definition": ""
    },
    {
      "language": "ru-RU",
      "name": "",
      "definition": ""
    }
  ],
  "applicableIfcClasses": [
    {
      "name": "IfcPerformanceHistory",
      "type": "IfcDistributionPort/AIRCONDITIONING[PerformanceHistory]"
    }
  ],
  "properties": [
    {
      "name": "Temperature",
      "definition": "Temperature of the fluid. For air this value represents the dry bulb temperature.",
      "dictionaryReference": {
        "dictionaryIdentifier": "http://bsdd.buildingsmart.org",
        "dictionaryNamespace": "PSet",
        "dictionaryWebUri": "http://bsdd.buildingsmart.org/#concept/browse/3JX$I0qTGHuO00025QrE$V",
        "dictionaryApiUri": "http://bsdd.buildingsmart.org/api/4.0/IfdConcept/3JX$I0qTGHuO00025QrE$V",
        "ifdGuid": "3JX$I0qTGHuO00025QrE$V",
        "legacyGuidAsIfcGlobalId": ""
      },
      "localizations": [
        {
          "language": "de-DE",
          "name": "",
          "definition": ""
        },
        {
          "language": "en-GB",
          "name": "",
          "definition": ""
        },
        {
          "language": "es-ES",
          "name": "",
          "definition": ""
        },
        {
          "language": "fr-FR",
          "name": "",
          "definition": ""
        },
        {
          "language": "ja-JP",
          "name": "",
          "definition": ""
        },
        {
          "language": "ru-RU",
          "name": "",
          "definition": ""
        }
      ],
      "typePropertyReferenceValue": {
        "refType": "IfcTimeSeries",
        "url": "http://buildingsmart-tech.org",
        "guid": "",
        "libraryName": "Industry Foundation Classes by buildingSMART International",
        "sectionref": "Core Schema"
      },
      "status": {
        "versionNumber": 4,
        "dateOfVersion": "2018-01-01T00:00:00",
        "revisionNumber": 2,
        "dateOfRevision": "2018-01-01T00:00:00",
        "status": "Active",
        "dateOfCreation": "2018-01-01T00:00:00",
        "dateOfActivation": "2018-01-01T00:00:00",
        "dateOfLastChange": "2018-01-01T00:00:00",
        "dateOfDeactivation": "0001-01-01T00:00:00",
        "languageOfCreator": "en-EN"
      }
    },
    {
      "name": "WetBulbTemperature",
      "definition": "Wet bulb temperature of the fluid; only applicable if the fluid is air.",
      "dictionaryReference": {
        "dictionaryIdentifier": "http://bsdd.buildingsmart.org",
        "dictionaryNamespace": "PSet",
        "dictionaryWebUri": "http://bsdd.buildingsmart.org/#concept/browse/3N6tk0qTGHuO00025QrE$V",
        "dictionaryApiUri": "http://bsdd.buildingsmart.org/api/4.0/IfdConcept/3N6tk0qTGHuO00025QrE$V",
        "ifdGuid": "3N6tk0qTGHuO00025QrE$V",
        "legacyGuidAsIfcGlobalId": ""
      },
      "localizations": [
        {
          "language": "de-DE",
          "name": "",
          "definition": ""
        },
        {
          "language": "en-GB",
          "name": "",
          "definition": ""
        },
        {
          "language": "es-ES",
          "name": "",
          "definition": ""
        },
        {
          "language": "fr-FR",
          "name": "",
          "definition": ""
        },
        {
          "language": "ja-JP",
          "name": "",
          "definition": ""
        },
        {
          "language": "ru-RU",
          "name": "",
          "definition": ""
        }
      ],
      "typePropertyReferenceValue": {
        "refType": "IfcTimeSeries",
        "url": "http://buildingsmart-tech.org",
        "guid": "",
        "libraryName": "Industry Foundation Classes by buildingSMART International",
        "sectionref": "Core Schema"
      },
      "status": {
        "versionNumber": 4,
        "dateOfVersion": "2018-01-01T00:00:00",
        "revisionNumber": 2,
        "dateOfRevision": "2018-01-01T00:00:00",
        "status": "Active",
        "dateOfCreation": "2018-01-01T00:00:00",
        "dateOfActivation": "2018-01-01T00:00:00",
        "dateOfLastChange": "2018-01-01T00:00:00",
        "dateOfDeactivation": "0001-01-01T00:00:00",
        "languageOfCreator": "en-EN"
      }
    },
    {
      "name": "VolumetricFlowRate",
      "definition": "The volumetric flow rate of the fluid.",
      "dictionaryReference": {
        "dictionaryIdentifier": "http://bsdd.buildingsmart.org",
        "dictionaryNamespace": "PSet",
        "dictionaryWebUri": "http://bsdd.buildingsmart.org/#concept/browse/3Q5cm0qTGHuO00025QrE$V",
        "dictionaryApiUri": "http://bsdd.buildingsmart.org/api/4.0/IfdConcept/3Q5cm0qTGHuO00025QrE$V",
        "ifdGuid": "3Q5cm0qTGHuO00025QrE$V",
        "legacyGuidAsIfcGlobalId": ""
      },
      "localizations": [
        {
          "language": "de-DE",
          "name": "",
          "definition": ""
        },
        {
          "language": "en-GB",
          "name": "",
          "definition": ""
        },
        {
          "language": "es-ES",
          "name": "",
          "definition": ""
        },
        {
          "language": "fr-FR",
          "name": "",
          "definition": ""
        },
        {
          "language": "ja-JP",
          "name": "",
          "definition": ""
        },
        {
          "language": "ru-RU",
          "name": "",
          "definition": ""
        }
      ],
      "typePropertyReferenceValue": {
        "refType": "IfcTimeSeries",
        "url": "http://buildingsmart-tech.org",
        "guid": "",
        "libraryName": "Industry Foundation Classes by buildingSMART International",
        "sectionref": "Core Schema"
      },
      "status": {
        "versionNumber": 4,
        "dateOfVersion": "2018-01-01T00:00:00",
        "revisionNumber": 2,
        "dateOfRevision": "2018-01-01T00:00:00",
        "status": "Active",
        "dateOfCreation": "2018-01-01T00:00:00",
        "dateOfActivation": "2018-01-01T00:00:00",
        "dateOfLastChange": "2018-01-01T00:00:00",
        "dateOfDeactivation": "0001-01-01T00:00:00",
        "languageOfCreator": "en-EN"
      }
    },
    {
      "name": "MassFlowRate",
      "definition": "The mass flow rate of the fluid.",
      "dictionaryReference": {
        "dictionaryIdentifier": "http://bsdd.buildingsmart.org",
        "dictionaryNamespace": "PSet",
        "dictionaryWebUri": "http://bsdd.buildingsmart.org/#concept/browse/3T4Lo0qTGHuO00025QrE$V",
        "dictionaryApiUri": "http://bsdd.buildingsmart.org/api/4.0/IfdConcept/3T4Lo0qTGHuO00025QrE$V",
        "ifdGuid": "3T4Lo0qTGHuO00025QrE$V",
        "legacyGuidAsIfcGlobalId": ""
      },
      "localizations": [
        {
          "language": "de-DE",
          "name": "",
          "definition": ""
        },
        {
          "language": "en-GB",
          "name": "",
          "definition": ""
        },
        {
          "language": "es-ES",
          "name": "",
          "definition": ""
        },
        {
          "language": "fr-FR",
          "name": "",
          "definition": ""
        },
        {
          "language": "ja-JP",
          "name": "",
          "definition": ""
        },
        {
          "language": "ru-RU",
          "name": "",
          "definition": ""
        }
      ],
      "typePropertyReferenceValue": {
        "refType": "IfcTimeSeries",
        "url": "http://buildingsmart-tech.org",
        "guid": "",
        "libraryName": "Industry Foundation Classes by buildingSMART International",
        "sectionref": "Core Schema"
      },
      "status": {
        "versionNumber": 4,
        "dateOfVersion": "2018-01-01T00:00:00",
        "revisionNumber": 2,
        "dateOfRevision": "2018-01-01T00:00:00",
        "status": "Active",
        "dateOfCreation": "2018-01-01T00:00:00",
        "dateOfActivation": "2018-01-01T00:00:00",
        "dateOfLastChange": "2018-01-01T00:00:00",
        "dateOfDeactivation": "0001-01-01T00:00:00",
        "languageOfCreator": "en-EN"
      }
    },
    {
      "name": "FlowCondition",
      "definition": "Defines the flow condition as a percentage of the cross-sectional area.",
      "dictionaryReference": {
        "dictionaryIdentifier": "http://bsdd.buildingsmart.org",
        "dictionaryNamespace": "PSet",
        "dictionaryWebUri": "http://bsdd.buildingsmart.org/#concept/browse/3W34q0qTGHuO00025QrE$V",
        "dictionaryApiUri": "http://bsdd.buildingsmart.org/api/4.0/IfdConcept/3W34q0qTGHuO00025QrE$V",
        "ifdGuid": "3W34q0qTGHuO00025QrE$V",
        "legacyGuidAsIfcGlobalId": ""
      },
      "localizations": [
        {
          "language": "de-DE",
          "name": "",
          "definition": ""
        },
        {
          "language": "en-GB",
          "name": "",
          "definition": ""
        },
        {
          "language": "es-ES",
          "name": "",
          "definition": ""
        },
        {
          "language": "fr-FR",
          "name": "",
          "definition": ""
        },
        {
          "language": "ja-JP",
          "name": "",
          "definition": ""
        },
        {
          "language": "ru-RU",
          "name": "",
          "definition": ""
        }
      ],
      "typePropertyReferenceValue": {
        "refType": "IfcTimeSeries",
        "url": "http://buildingsmart-tech.org",
        "guid": "",
        "libraryName": "Industry Foundation Classes by buildingSMART International",
        "sectionref": "Core Schema"
      },
      "status": {
        "versionNumber": 4,
        "dateOfVersion": "2018-01-01T00:00:00",
        "revisionNumber": 2,
        "dateOfRevision": "2018-01-01T00:00:00",
        "status": "Active",
        "dateOfCreation": "2018-01-01T00:00:00",
        "dateOfActivation": "2018-01-01T00:00:00",
        "dateOfLastChange": "2018-01-01T00:00:00",
        "dateOfDeactivation": "0001-01-01T00:00:00",
        "languageOfCreator": "en-EN"
      }
    },
    {
      "name": "Velocity",
      "definition": "The velocity of the fluid.",
      "dictionaryReference": {
        "dictionaryIdentifier": "http://bsdd.buildingsmart.org",
        "dictionaryNamespace": "PSet",
        "dictionaryWebUri": "http://bsdd.buildingsmart.org/#concept/browse/3ZdzG0qTGHuO00025QrE$V",
        "dictionaryApiUri": "http://bsdd.buildingsmart.org/api/4.0/IfdConcept/3ZdzG0qTGHuO00025QrE$V",
        "ifdGuid": "3ZdzG0qTGHuO00025QrE$V",
        "legacyGuidAsIfcGlobalId": ""
      },
      "localizations": [
        {
          "language": "de-DE",
          "name": "",
          "definition": ""
        },
        {
          "language": "en-GB",
          "name": "",
          "definition": ""
        },
        {
          "language": "es-ES",
          "name": "",
          "definition": ""
        },
        {
          "language": "fr-FR",
          "name": "",
          "definition": ""
        },
        {
          "language": "ja-JP",
          "name": "",
          "definition": ""
        },
        {
          "language": "ru-RU",
          "name": "",
          "definition": ""
        }
      ],
      "typePropertyReferenceValue": {
        "refType": "IfcTimeSeries",
        "url": "http://buildingsmart-tech.org",
        "guid": "",
        "libraryName": "Industry Foundation Classes by buildingSMART International",
        "sectionref": "Core Schema"
      },
      "status": {
        "versionNumber": 4,
        "dateOfVersion": "2018-01-01T00:00:00",
        "revisionNumber": 2,
        "dateOfRevision": "2018-01-01T00:00:00",
        "status": "Active",
        "dateOfCreation": "2018-01-01T00:00:00",
        "dateOfActivation": "2018-01-01T00:00:00",
        "dateOfLastChange": "2018-01-01T00:00:00",
        "dateOfDeactivation": "0001-01-01T00:00:00",
        "languageOfCreator": "en-EN"
      }
    },
    {
      "name": "Pressure",
      "definition": "The pressure of the fluid.",
      "dictionaryReference": {
        "dictionaryIdentifier": "http://bsdd.buildingsmart.org",
        "dictionaryNamespace": "PSet",
        "dictionaryWebUri": "http://bsdd.buildingsmart.org/#concept/browse/3cciI0qTGHuO00025QrE$V",
        "dictionaryApiUri": "http://bsdd.buildingsmart.org/api/4.0/IfdConcept/3cciI0qTGHuO00025QrE$V",
        "ifdGuid": "3cciI0qTGHuO00025QrE$V",
        "legacyGuidAsIfcGlobalId": ""
      },
      "localizations": [
        {
          "language": "de-DE",
          "name": "",
          "definition": ""
        },
        {
          "language": "en-GB",
          "name": "",
          "definition": ""
        },
        {
          "language": "es-ES",
          "name": "",
          "definition": ""
        },
        {
          "language": "fr-FR",
          "name": "",
          "definition": ""
        },
        {
          "language": "ja-JP",
          "name": "",
          "definition": ""
        },
        {
          "language": "ru-RU",
          "name": "",
          "definition": ""
        }
      ],
      "typePropertyReferenceValue": {
        "refType": "IfcTimeSeries",
        "url": "http://buildingsmart-tech.org",
        "guid": "",
        "libraryName": "Industry Foundation Classes by buildingSMART International",
        "sectionref": "Core Schema"
      },
      "status": {
        "versionNumber": 4,
        "dateOfVersion": "2018-01-01T00:00:00",
        "revisionNumber": 2,
        "dateOfRevision": "2018-01-01T00:00:00",
        "status": "Active",
        "dateOfCreation": "2018-01-01T00:00:00",
        "dateOfActivation": "2018-01-01T00:00:00",
        "dateOfLastChange": "2018-01-01T00:00:00",
        "dateOfDeactivation": "0001-01-01T00:00:00",
        "languageOfCreator": "en-EN"
      }
    }
  ]
}